{
    "schedule": {
        "DUK": {
            "TSA": {
                "sailingDuration": "2h 0m",
                "sailings": [
                    {
                        "time": "3:15PM",
                        "fill": 88,
                        "carFill": 91,
                        "oversizeFill": 86,
                        "vesselName": "Coastal Inspiration",
                        "vesselStatus": ""
                    },
                    {
                        "time": "5:45PM",
                        "fill": 70,
                        "carFill": 49,
                        "oversizeFill": 91,
                        "vesselName": "Queen of Alberni",
                        "vesselStatus": ""
                    },
                    {
                        "time": "8:15PM",
                        "fill": 51,
                        "carFill": 41,
                        "oversizeFill": 61,
                        "vesselName": "Coastal Inspiration",
                        "vesselStatus": ""
                    },
                    {
                        "time": "10:45PM",
                        "fill": 44,
                        "carFill": 14,
                        "oversizeFill": 72,
                        "vesselName": "Queen of Alberni",
                        "vesselStatus": ""
                    },
                    {
                        "time": "5:15AM",
                        "fill": 36,
                        "carFill": 16,
                        "oversizeFill": 57,
                        "vesselName": "Coastal Inspiration",
                        "vesselStatus": ""
                    },
                    {
                        "time": "7:45AM",
                        "fill": 65,
                        "carFill": 66,
                        "oversizeFill": 64,
                        "vesselName": "Queen of Alberni",
                        "vesselStatus": ""
                    },
                    {
                        "time": "10:15AM",
                        "fill": 58,
                        "carFill": 54,
                        "oversizeFill": 61,
                        "vesselName": "Coastal Inspiration",
                        "vesselStatus": ""
                    }
                ]
            }
        },
        "HSB": {
            "BOW": {
                "sailingDuration": "0h 20m",
                "sailings": [
                    {
                        "time": "2:20PM",
                        "fill": 36,
                        "carFill": 50,
                        "oversizeFill": 0,
                        "vesselName": "Queen of Capilano",
                        "vesselStatus": ""
                    },
                    {
                        "time": "3:30PM",
                        "fill": 0,
                        "carFill": 0,
                        "oversizeFill": 0,
                        "vesselName": "Queen of Capilano",
                        "vesselStatus": ""
                    },
                    {
                        "time": "4:35PM",
                        "fill": 0,
                        "carFill": 0,
                        "oversizeFill": 0,
                        "vesselName": "Queen of Capilano",
                        "vesselStatus": ""
                    },
                    {
                        "time": "5:45PM",
                        "fill": 0,
                        "carFill": 0,
                        "oversizeFill": 0,
                        "vesselName": "Queen of Capilano",
                        "vesselStatus": ""
                    },
                    {
                        "time": "6:50PM",
                        "fill": 0,
                        "carFill": 0,
                        "oversizeFill": 0,
                        "vesselName": "Queen of Capilano",
                        "vesselStatus": ""
                    },
                    {
                        "time": "8:20PM",
                        "fill": 0,
                        "carFill": 0,
                        "oversizeFill": 0,
                        "vesselName": "Queen of Capilano",
                        "vesselStatus": ""
                    },
                    {
                        "time": "9:30PM",
                        "fill": 0,
                        "carFill": 0,
                        "oversizeFill": 0,
                        "vesselName": "Queen of Capilano",
                        "vesselStatus": ""
                    },
                    {
                        "time": "10:30PM",
                        "fill": 0,
                        "carFill": 0,
                        "oversizeFill": 0,
                        "vesselName": "Queen of Capilano",
                        "vesselStatus": ""
                    },
                    {
                        "time": "5:50AM",
                        "fill": 0,
                        "carFill": 0,
                        "oversizeFill": 0,
                        "vesselName": "Queen of Capilano",
                        "vesselStatus": ""
                    },
                    {
                        "time": "6:50AM",
                        "fill": 0,
                        "carFill": 0,
                        "oversizeFill": 0,
                        "vesselName": "Queen of Capilano",
                        "vesselStatus": ""
                    },
                    {
                        "time": "8:00AM",
                        "fill": 0,
                        "carFill": 0,
                        "oversizeFill": 0,
                        "vesselName": "Queen of Capilano",
                        "vesselStatus": ""
                    }
                ]
            },
            "LNG": {
                "sailingDuration": "0h 40m",
                "sailings": [
                    {
                        "time": "2:10PM",
                        "fill": 100,
                        "carFill": 100,
                        "oversizeFill": 100,
                        "vesselName": "Queen of Coquitlam",
                        "vesselStatus": ""
                    },
                    {
                        "time": "4:20PM",
                        "fill": 29,
                        "carFill": 34,
                        "oversizeFill": 16,
                        "vesselName": "Queen of Coquitlam",
                        "vesselStatus": ""
                    },
                    {
                        "time": "6:35PM",
                        "fill": 27,
                        "carFill": 26,
                        "oversizeFill": 31,
                        "vesselName": "Queen of Coquitlam",
                        "vesselStatus": ""
                    },
                    {
                        "time": "8:45PM",
                        "fill": 20,
                        "carFill": 17,
                        "oversizeFill": 26,
                        "vesselName": "Queen of Coquitlam",
                        "vesselStatus": ""
                    },
                    {
                        "time": "10:55PM",
                        "fill": 5,
                        "carFill": 16,
                        "oversizeFill": 0,
                        "vesselName": "Queen of Coquitlam",
                        "vesselStatus": ""
                    },
                    {
                        "time": "7:30AM",
                        "fill": 45,
                        "carFill": 31,
                        "oversizeFill": 80,
                        "vesselName": "Queen of Coquitlam",
                        "vesselStatus": ""
                    },
                    {
                        "time": "9:45AM",
                        "fill": 42,
                        "carFill": 34,
                        "oversizeFill": 63,
                        "vesselName": "Queen of Coquitlam",
                        "vesselStatus": ""
                    },
                    {
                        "time": "11:55AM",
                        "fill": 42,
                        "carFill": 34,
                        "oversizeFill": 61,
                        "vesselName": "Queen of Coquitlam",
                        "vesselStatus": ""
                    }
                ]
            },
            "NAN": {
                "sailingDuration": "1h 40m",
                "sailings": [
                    {
                        "time": "3:45PM",
                        "fill": 61,
                        "carFill": 66,
                        "oversizeFill": 47,
                        "vesselName": "Queen of Oak Bay",
                        "vesselStatus": ""
                    },
                    {
                        "time": "5:40PM",
                        "fill": 41,
                        "carFill": 50,
                        "oversizeFill": 20,
                        "vesselName": "Queen of Cowichan",
                        "vesselStatus": ""
                    },
                    {
                        "time": "8:05PM",
                        "fill": 35,
                        "carFill": 38,
                        "oversizeFill": 28,
                        "vesselName": "Queen of Oak Bay",
                        "vesselStatus": ""
                    },
                    {
                        "time": "6:15AM",
                        "fill": 36,
                        "carFill": 35,
                        "oversizeFill": 38,
                        "vesselName": "Queen of Oak Bay",
                        "vesselStatus": ""
                    },
                    {
                        "time": "8:25AM",
                        "fill": 48,
                        "carFill": 52,
                        "oversizeFill": 38,
                        "vesselName": "Queen of Cowichan",
                        "vesselStatus": ""
                    },
                    {
                        "time": "10:40AM",
                        "fill": 44,
                        "carFill": 52,
                        "oversizeFill": 24,
                        "vesselName": "Queen of Oak Bay",
                        "vesselStatus": ""
                    }
                ]
            }
        },
        "LNG": {
            "HSB": {
                "sailingDuration": "0h 40m",
                "sailings": [
                    {
                        "time": "3:15PM",
                        "fill": 49,
                        "carFill": 43,
                        "oversizeFill": 63,
                        "vesselName": "Queen of Coquitlam",
                        "vesselStatus": ""
                    },
                    {
                        "time": "5:25PM",
                        "fill": 29,
                        "carFill": 23,
                        "oversizeFill": 44,
                        "vesselName": "Queen of Coquitlam",
                        "vesselStatus": ""
                    },
                    {
                        "time": "7:40PM",
                        "fill": 10,
                        "carFill": 9,
                        "oversizeFill": 13,
                        "vesselName": "Queen of Coquitlam",
                        "vesselStatus": ""
                    },
                    {
                        "time": "9:50PM",
                        "fill": 3,
                        "carFill": 2,
                        "oversizeFill": 6,
                        "vesselName": "Queen of Coquitlam",
                        "vesselStatus": ""
                    },
                    {
                        "time": "6:20AM",
                        "fill": 11,
                        "carFill": 3,
                        "oversizeFill": 32,
                        "vesselName": "Queen of Coquitlam",
                        "vesselStatus": ""
                    },
                    {
                        "time": "8:40AM",
                        "fill": 35,
                        "carFill": 36,
                        "oversizeFill": 32,
                        "vesselName": "Queen of Coquitlam",
                        "vesselStatus": ""
                    },
                    {
                        "time": "10:50AM",
                        "fill": 35,
                        "carFill": 34,
                        "oversizeFill": 40,
                        "vesselName": "Queen of Coquitlam",
                        "vesselStatus": ""
                    }
                ]
            }
        },
        "NAN": {
            "HSB": {
                "sailingDuration": "1h 40m",
                "sailings": [
                    {
                        "time": "3:20PM",
                        "fill": 100,
                        "carFill": 100,
                        "oversizeFill": 100,
                        "vesselName": "Queen of Cowichan",
                        "vesselStatus": ""
                    },
                    {
                        "time": "5:55PM",
                        "fill": 71,
                        "carFill": 76,
                        "oversizeFill": 56,
                        "vesselName": "Queen of Oak Bay",
                        "vesselStatus": ""
                    },
                    {
                        "time": "10:10PM",
                        "fill": 20,
                        "carFill": 16,
                        "oversizeFill": 28,
                        "vesselName": "Queen of Oak Bay",
                        "vesselStatus": ""
                    },
                    {
                        "time": "6:15AM",
                        "fill": 26,
                        "carFill": 28,
                        "oversizeFill": 22,
                        "vesselName": "Queen of Cowichan",
                        "vesselStatus": ""
                    },
                    {
                        "time": "8:25AM",
                        "fill": 47,
                        "carFill": 63,
                        "oversizeFill": 5,
                        "vesselName": "Queen of Oak Bay",
                        "vesselStatus": ""
                    },
                    {
                        "time": "10:40AM",
                        "fill": 63,
                        "carFill": 77,
                        "oversizeFill": 27,
                        "vesselName": "Queen of Cowichan",
                        "vesselStatus": ""
                    }
                ]
            }
        },
        "SWB": {
            "FUL": {
                "sailingDuration": "0h 35m",
                "sailings": [
                    {
                        "time": "3:00PM",
                        "fill": 9,
                        "carFill": 9,
                        "oversizeFill": 0,
                        "vesselName": "Skeena Queen",
                        "vesselStatus": ""
                    },
                    {
                        "time": "5:00PM",
                        "fill": 0,
                        "carFill": 0,
                        "oversizeFill": 0,
                        "vesselName": "Skeena Queen",
                        "vesselStatus": ""
                    },
                    {
                        "time": "7:00PM",
                        "fill": 0,
                        "carFill": 0,
                        "oversizeFill": 0,
                        "vesselName": "Skeena Queen",
                        "vesselStatus": ""
                    },
                    {
                        "time": "9:00PM",
                        "fill": 0,
                        "carFill": 0,
                        "oversizeFill": 0,
                        "vesselName": "Skeena Queen",
                        "vesselStatus": ""
                    },
                    {
                        "time": "7:00AM",
                        "fill": 0,
                        "carFill": 0,
                        "oversizeFill": 0,
                        "vesselName": "Skeena Queen",
                        "vesselStatus": ""
                    },
                    {
                        "time": "9:00AM",
                        "fill": 0,
                        "carFill": 0,
                        "oversizeFill": 0,
                        "vesselName": "Skeena Queen",
                        "vesselStatus": ""
                    },
                    {
                        "time": "11:00AM",
                        "fill": 0,
                        "carFill": 0,
                        "oversizeFill": 0,
                        "vesselName": "Skeena Queen",
                        "vesselStatus": ""
                    }
                ]
            },
            "SGI": {
                "sailingDuration": "Varies",
                "sailings": [
                    {
                        "time": "2:20PM",
                        "fill": 100,
                        "carFill": 100,
                        "oversizeFill": 0,
                        "vesselName": "Queen of Cumberland",
                        "vesselStatus": ""
                    },
                    {
                        "time": "3:10PM",
                        "fill": 17,
                        "carFill": 17,
                        "oversizeFill": 0,
                        "vesselName": "Mayne Queen",
                        "vesselStatus": ""
                    },
                    {
                        "time": "4:20PM",
                        "fill": 0,
                        "carFill": 0,
                        "oversizeFill": 0,
                        "vesselName": "Queen of Cumberland",
                        "vesselStatus": ""
                    },
                    {
                        "time": "6:40PM",
                        "fill": 0,
                        "carFill": 0,
                        "oversizeFill": 0,
                        "vesselName": "Queen of Cumberland",
                        "vesselStatus": ""
                    },
                    {
                        "time": "7:55PM",
                        "fill": 0,
                        "carFill": 0,
                        "oversizeFill": 0,
                        "vesselName": "Mayne Queen",
                        "vesselStatus": ""
                    },
                    {
                        "time": "5:00AM",
                        "fill": 0,
                        "carFill": 0,
                        "oversizeFill": 0,
                        "vesselName": "Mayne Queen",
                        "vesselStatus": ""
                    },
                    {
                        "time": "5:05AM",
                        "fill": 0,
                        "carFill": 0,
                        "oversizeFill": 0,
                        "vesselName": "Queen of Cumberland",
                        "vesselStatus": ""
                    },
                    {
                        "time": "8:15AM",
                        "fill": 0,
                        "carFill": 0,
                        "oversizeFill": 0,
                        "vesselName": "Queen of Cumberland",
                        "vesselStatus": ""
                    }
                ]
            },
            "TSA": {
                "sailingDuration": "1h 35m",
                "sailings": [
                    {
                        "time": "3:00PM",
                        "fill": 100,
                        "carFill": 100,
                        "oversizeFill": 100,
                        "vesselName": "Spirit of Vancouver Island",
                        "vesselStatus": ""
                    },
                    {
                        "time": "5:00PM",
                        "fill": 95,
                        "carFill": 100,
                        "oversizeFill": 91,
                        "vesselName": "Spirit of British Columbia",
                        "vesselStatus": ""
                    },
                    {
                        "time": "7:00PM",
                        "fill": 75,
                        "carFill": 95,
                        "oversizeFill": 55,
                        "vesselName": "Spirit of Vancouver Island",
                        "vesselStatus": ""
                    },
                    {
                        "time": "9:00PM",
                        "fill": 70,
                        "carFill": 86,
                        "oversizeFill": 54,
                        "vesselName": "Spirit of British Columbia",
                        "vesselStatus": ""
                    },
                    {
                        "time": "7:00AM",
                        "fill": 86,
                        "carFill": 87,
                        "oversizeFill": 85,
                        "vesselName": "Spirit of Vancouver Island",
                        "vesselStatus": ""
                    },
                    {
                        "time": "9:00AM",
                        "fill": 74,
                        "carFill": 95,
                        "oversizeFill": 53,
                        "vesselName": "Spirit of British Columbia",
                        "vesselStatus": ""
                    },
                    {
                        "time": "11:00AM",
                        "fill": 79,
                        "carFill": 89,
                        "oversizeFill": 70,
                        "vesselName": "Spirit of Vancouver Island",
                        "vesselStatus": ""
                    }
                ]
            }
        },
        "TSA": {
            "DUK": {
                "sailingDuration": "2h 0m",
                "sailings": [
                    {
                        "time": "3:15PM",
                        "fill": 90,
                        "carFill": 88,
                        "oversizeFill": 91,
                        "vesselName": "Queen of Alberni",
                        "vesselStatus": ""
                    },
                    {
                        "time": "5:45PM",
                        "fill": 58,
                        "carFill": 37,
                        "oversizeFill": 79,
                        "vesselName": "Coastal Inspiration",
                        "vesselStatus": ""
                    },
                    {
                        "time": "8:15PM",
                        "fill": 58,
                        "carFill": 29,
                        "oversizeFill": 86,
                        "vesselName": "Queen of Alberni",
                        "vesselStatus": ""
                    },
                    {
                        "time": "10:45PM",
                        "fill": 46,
                        "carFill": 3,
                        "oversizeFill": 90,
                        "vesselName": "Coastal Inspiration",
                        "vesselStatus": ""
                    },
                    {
                        "time": "5:15AM",
                        "fill": 50,
                        "carFill": 14,
                        "oversizeFill": 85,
                        "vesselName": "Queen of Alberni",
                        "vesselStatus": ""
                    },
                    {
                        "time": "7:45AM",
                        "fill": 60,
                        "carFill": 38,
                        "oversizeFill": 82,
                        "vesselName": "Coastal Inspiration",
                        "vesselStatus": ""
                    },
                    {
                        "time": "10:15AM",
                        "fill": 80,
                        "carFill": 84,
                        "oversizeFill": 77,
                        "vesselName": "Queen of Alberni",
                        "vesselStatus": ""
                    }
                ]
            },
            "SGI": {
                "sailingDuration": "Varies",
                "sailings": [
                    {
                        "time": "7:10PM",
                        "fill": 100,
                        "carFill": 100,
                        "oversizeFill": 100,
                        "vesselName": "Salish Eagle",
                        "vesselStatus": ""
                    },
                    {
                        "time": "9:55AM",
                        "fill": 100,
                        "carFill": 100,
                        "oversizeFill": 100,
                        "vesselName": "Salish Eagle",
                        "vesselStatus": ""
                    },
                    {
                        "time": "7:10PM",
                        "fill": 100,
                        "carFill": 100,
                        "oversizeFill": 100,
                        "vesselName": "Salish Eagle",
                        "vesselStatus": ""
                    },
                    {
                        "time": "9:55AM\n\n\n(Mar25,2022)",
                        "fill": 98,
                        "carFill": 100,
                        "oversizeFill": 97,
                        "vesselName": "Salish Eagle",
                        "vesselStatus": ""
                    }
                ]
            },
            "SWB": {
                "sailingDuration": "1h 35m",
                "sailings": [
                    {
                        "time": "3:00PM",
                        "fill": 100,
                        "carFill": 100,
                        "oversizeFill": 100,
                        "vesselName": "Spirit of British Columbia",
                        "vesselStatus": ""
                    },
                    {
                        "time": "5:00PM",
                        "fill": 100,
                        "carFill": 100,
                        "oversizeFill": 100,
                        "vesselName": "Spirit of Vancouver Island",
                        "vesselStatus": ""
                    },
                    {
                        "time": "7:00PM",
                        "fill": 80,
                        "carFill": 100,
                        "oversizeFill": 61,
                        "vesselName": "Spirit of British Columbia",
                        "vesselStatus": ""
                    },
                    {
                        "time": "9:00PM",
                        "fill": 65,
                        "carFill": 56,
                        "oversizeFill": 74,
                        "vesselName": "Spirit of Vancouver Island",
                        "vesselStatus": ""
                    },
                    {
                        "time": "7:00AM",
                        "fill": 88,
                        "carFill": 86,
                        "oversizeFill": 90,
                        "vesselName": "Spirit of British Columbia",
                        "vesselStatus": ""
                    },
                    {
                        "time": "9:00AM",
                        "fill": 76,
                        "carFill": 99,
                        "oversizeFill": 53,
                        "vesselName": "Spirit of Vancouver Island",
                        "vesselStatus": ""
                    },
                    {
                        "time": "11:00AM",
                        "fill": 63,
                        "carFill": 62,
                        "oversizeFill": 64,
                        "vesselName": "Spirit of British Columbia",
                        "vesselStatus": ""
                    }
                ]
            }
        }
    },
    "scrapedAt": "2022-03-23T13:49:21.269712-07:00"
}